zeno_etl_libs/README.md
zeno_etl_libs/__init__.py
zeno_etl_libs/setup.py
zeno_etl_libs/config/__init__.py
zeno_etl_libs/config/common.py
zeno_etl_libs/db/__init__.py
zeno_etl_libs/db/db.py
zeno_etl_libs/django/__init__.py
zeno_etl_libs/django/api.py
zeno_etl_libs/helper/__init__.py
zeno_etl_libs/helper/helper.py
zeno_etl_libs/helper/aws/__init__.py
zeno_etl_libs/helper/aws/crawler.py
zeno_etl_libs/helper/aws/dms.py
zeno_etl_libs/helper/aws/glue.py
zeno_etl_libs/helper/aws/redshift.py
zeno_etl_libs/helper/aws/s3.py
zeno_etl_libs/helper/clervertap/__init__.py
zeno_etl_libs/helper/clervertap/clevertap.py
zeno_etl_libs/helper/clervertap/clevertap_2.py
zeno_etl_libs/helper/disprz/__init__.py
zeno_etl_libs/helper/disprz/disprz.py
zeno_etl_libs/helper/email/__init__.py
zeno_etl_libs/helper/email/email.py
zeno_etl_libs/helper/fresh_service/__init__.py
zeno_etl_libs/helper/fresh_service/fresh_service.py
zeno_etl_libs/helper/google/__init__.py
zeno_etl_libs/helper/google/playstore/__init__.py
zeno_etl_libs/helper/google/playstore/playstore.py
zeno_etl_libs/helper/google/sheet/__init__.py
zeno_etl_libs/helper/google/sheet/sheet.py
zeno_etl_libs/helper/parameter/__init__.py
zeno_etl_libs/helper/parameter/job_parameter.py
zeno_etl_libs/helper/run_notebook/__init__.py
zeno_etl_libs/helper/run_notebook/run_notebook.py
zeno_etl_libs/helper/tableau/__init__.py
zeno_etl_libs/helper/tableau/tableau.py
zeno_etl_libs/helper/websocket/__init__.py
zeno_etl_libs/helper/websocket/websocket.py
zeno_etl_libs/logger/__init__.py
zeno_etl_libs/mymath/__init__.py
zeno_etl_libs/mymath/add.py
zeno_etl_libs/mymath/divide.py
zeno_etl_libs/mymath/mods_packs.wpr
zeno_etl_libs/mymath/mods_packs.wpu
zeno_etl_libs/mymath/multiply.py
zeno_etl_libs/mymath/subtract.py
zeno_etl_libs/mymath/adv/__init__.py
zeno_etl_libs/mymath/adv/fib.py
zeno_etl_libs/mymath/adv/sqrt.py
zeno_etl_libs/notification/__init__.py
zeno_etl_libs/notification/notification_util.py
zeno_etl_libs/queries/__init__.py
zeno_etl_libs_v3-1.0.17.dist-info/METADATA
zeno_etl_libs_v3-1.0.17.dist-info/WHEEL
zeno_etl_libs_v3-1.0.17.dist-info/entry_points.txt
zeno_etl_libs_v3-1.0.17.dist-info/top_level.txt
zeno_etl_libs_v3-1.0.17.dist-info/RECORD
